DataCentricKMeans/DataCentricKMeans.py
DataCentricKMeans/DataCentricKMeans_linux.out
DataCentricKMeans/DataCentricKMeans_universal.out
DataCentricKMeans/DataCentricKMeans_windows.exe
DataCentricKMeans/__init__.py
DataCentricKMeans-0.8.dist-info/METADATA
DataCentricKMeans-0.8.dist-info/WHEEL
DataCentricKMeans-0.8.dist-info/top_level.txt
DataCentricKMeans-0.8.dist-info/RECORD
