Metadata-Version: 2.1
Name: DataCentricKMeans
Version: 0.8
Summary: A package for running DataCentricKMeans.
Home-page: https://github.com/brainvs/DataCentricKMeansPython
Author: Vasfi Tataroglu, Parichit Sharma, Hasan Kurban, and Mehmet M. Dalkilic
Author-email: vtatarog@iu.edu
Classifier: Programming Language :: Python :: 3
Classifier: License :: OSI Approved :: MIT License
Classifier: Operating System :: OS Independent
Requires-Python: >=3.6
